scpantheon/__init__.py
scpantheon/main.py
scpantheon/source.py
scpantheon/app/__init__.py
scpantheon/app/bokeh_qt.py
scpantheon/front_end/__init__.py
scpantheon/front_end/data_qt.py
scpantheon/front_end/extensions_qt.py
scpantheon/front_end/load_qt.py
scpantheon/front_end/save_qt.py
scPANTHEON-0.5.5.3.dist-info/METADATA
scPANTHEON-0.5.5.3.dist-info/WHEEL
scPANTHEON-0.5.5.3.dist-info/entry_points.txt
scPANTHEON-0.5.5.3.dist-info/top_level.txt
scPANTHEON-0.5.5.3.dist-info/RECORD
