Metadata-Version: 2.1
Name: scPANTHEON
Version: 0.5.5.3
Summary: A graphical interface for single cell analysis.
Home-page: https://github.com/xinzhu-email/Pantheon
Author: xinzhu
Author-email: xinzhu.jiang@sjtu.edu.cn
License: MIT
Requires-Dist: bokeh (==2.4.3)
Requires-Dist: pandas
Requires-Dist: anndata
Requires-Dist: colorcet
Requires-Dist: scanpy
Requires-Dist: numpy
Requires-Dist: PyQt5
Requires-Dist: PyQtWebEngine
Requires-Dist: appdirs
Requires-Dist: requests
Requires-Dist: leidenalg
Requires-Dist: setuptools-scm
